setup.py
gabi_probs/Binomialdistribution.py
gabi_probs/Gaussiandistribution.py
gabi_probs/Generaldistribution.py
gabi_probs/__init__.py
gabi_probs.egg-info/PKG-INFO
gabi_probs.egg-info/SOURCES.txt
gabi_probs.egg-info/dependency_links.txt
gabi_probs.egg-info/not-zip-safe
gabi_probs.egg-info/top_level.txt