Metadata-Version: 1.0
Name: gabi-probs
Version: 1.0
Summary: Gaussian and Binomail distributions
Home-page: UNKNOWN
Author: Ceren Yaşar
Author-email: UNKNOWN
License: UNKNOWN
Platform: UNKNOWN
